model_library/__init__.py
model_library/exceptions.py
model_library/file_utils.py
model_library/logging.py
model_library/model_utils.py
model_library/py.typed
model_library/register_models.py
model_library/registry_utils.py
model_library/settings.py
model_library/utils.py
model_library/base/__init__.py
model_library/base/base.py
model_library/base/batch.py
model_library/base/delegate_only.py
model_library/base/input.py
model_library/base/output.py
model_library/base/utils.py
model_library/config/README.md
model_library/config/ai21labs_models.yaml
model_library/config/alibaba_models.yaml
model_library/config/all_models.json
model_library/config/amazon_models.yaml
model_library/config/anthropic_models.yaml
model_library/config/cohere_models.yaml
model_library/config/deepseek_models.yaml
model_library/config/dummy_model.yaml
model_library/config/fireworks_models.yaml
model_library/config/google_models.yaml
model_library/config/inception_models.yaml
model_library/config/kimi_models.yaml
model_library/config/minimax_models.yaml
model_library/config/mistral_models.yaml
model_library/config/openai_models.yaml
model_library/config/perplexity_models.yaml
model_library/config/together_models.yaml
model_library/config/xai_models.yaml
model_library/config/zai_models.yaml
model_library/providers/__init__.py
model_library/providers/ai21labs.py
model_library/providers/alibaba.py
model_library/providers/amazon.py
model_library/providers/anthropic.py
model_library/providers/azure.py
model_library/providers/cohere.py
model_library/providers/deepseek.py
model_library/providers/fireworks.py
model_library/providers/inception.py
model_library/providers/kimi.py
model_library/providers/minimax.py
model_library/providers/mistral.py
model_library/providers/openai.py
model_library/providers/perplexity.py
model_library/providers/together.py
model_library/providers/vals.py
model_library/providers/xai.py
model_library/providers/zai.py
model_library/providers/google/__init__.py
model_library-0.1.5.dist-info/licenses/LICENSE
model_library-0.1.5.dist-info/METADATA
model_library-0.1.5.dist-info/WHEEL
model_library-0.1.5.dist-info/top_level.txt
model_library-0.1.5.dist-info/RECORD
