Metadata-Version: 2.4
Name: model-library
Version: 0.1.5
Summary: Model Library for vals.ai 
Author-email: "Vals AI, Inc." <contact@vals.ai>
License: MIT
Requires-Python: >=3.11
License-File: LICENSE
Requires-Dist: typing-extensions<5.0,>=4.14.1
Requires-Dist: pydantic<3.0,>=2.11.7
Requires-Dist: pyyaml>=6.0.2
Requires-Dist: rich
Requires-Dist: backoff<3.0,>=2.2.1
Requires-Dist: redis<7.0,>=6.2.0
Requires-Dist: tiktoken==0.11.0
Requires-Dist: pillow
Requires-Dist: openai<3.0,>=2.0
Requires-Dist: anthropic<1.0,>=0.57.1
Requires-Dist: mistralai<2.0,>=1.9.10
Requires-Dist: xai-sdk<2.0,>=1.0.0
Requires-Dist: ai21<5.0,>=4.0.3
Requires-Dist: boto3<2.0,>=1.38.27
Requires-Dist: google-genai[aiohttp]>=1.51.0
Requires-Dist: google-cloud-storage>=1.26.0
Dynamic: license-file
